{"cameraMode":{"drawMode":0,"name":"Shaded","section":"Shading Mode"},"sceneLighting":false,"audioPlay":false,"sceneViewState":{"showFog":true,"showMaterialUpdate":false,"showSkybox":false,"showFlares":true,"showImageEffects":true,"showParticleSystems":true},"in2DMode":false,"pivot":{"x":1.1650004386901856,"y":1.5710887908935547,"z":-14.87757682800293},"rotation":{"x":0.2979368567466736,"y":0.06752169877290726,"z":-0.02113289386034012,"w":0.951960027217865},"size":8.431012153625489,"orthographic":false}